python_wrapper/__init__.py
python_wrapper/client.py
python_wrapper.egg-info/PKG-INFO
python_wrapper.egg-info/SOURCES.txt
python_wrapper.egg-info/dependency_links.txt
python_wrapper.egg-info/requires.txt
python_wrapper.egg-info/top_level.txt
python_wrapper-0.1.0.dist-info/LICENSE
python_wrapper-0.1.0.dist-info/METADATA
python_wrapper-0.1.0.dist-info/WHEEL
python_wrapper-0.1.0.dist-info/top_level.txt
python_wrapper-0.1.0.dist-info/RECORD
